MANIFEST.in
requirements.txt
setup.py
tornado_content_negotiation.py
tornado_content_negotiation.egg-info/PKG-INFO
tornado_content_negotiation.egg-info/SOURCES.txt
tornado_content_negotiation.egg-info/dependency_links.txt
tornado_content_negotiation.egg-info/requires.txt
tornado_content_negotiation.egg-info/top_level.txt