Metadata-Version: 1.1
Name: tornado-content-negotiation
Version: 0.2.2
Summary: Content Negotiation module for Tornado.
Home-page: https://github.com/globocom/tornado_content_negotiation
Author: globo.com
Author-email: guilherme.cirne@corp.globo.com
License: MIT
Keywords: tornado content-negotiation
Platform: UNKNOWN
Classifier: Development Status :: 4 - Beta
Classifier: Intended Audience :: Developers
Classifier: License :: OSI Approved :: MIT License
Classifier: Natural Language :: English
Classifier: Operating System :: MacOS
Classifier: Operating System :: POSIX :: Linux
Classifier: Programming Language :: Python :: 2.7
Classifier: Programming Language :: Python :: 3.2
Classifier: Programming Language :: Python :: 3.3
Classifier: Topic :: Software Development :: Libraries
